README.md
setup.py
Areix_IO.egg-info/PKG-INFO
Areix_IO.egg-info/SOURCES.txt
Areix_IO.egg-info/dependency_links.txt
Areix_IO.egg-info/not-zip-safe
Areix_IO.egg-info/requires.txt
Areix_IO.egg-info/top_level.txt
areix_io/MIrsZTteqgoyIbdDfzCfQSeevwvHcwrX.py
areix_io/SLCHMjNdxVZEQIneqgprbyjfuVVIwwxh.py
areix_io/__init__.py
areix_io/hikWkBoRVJhcJmkQwwmZilXBLFjTNVbv.py
areix_io/nRnGoocCsCfasKrgkFdAdwFnxPsAwKPZ.py
areix_io/tnMqpXOIYgmFptmanhNgIlELCyoxsTCW.py
areix_io/wuVFCzbvzCpZVRgZwQSsRNtAGaufiTdC.py
areix_io/exchanges/MAXroNOqhLnGxCLjHVTIEORmZWRqbjiF.py
areix_io/exchanges/__init__.py
areix_io/exchanges/gHoLzqioHOVbMQWDnMgtnsWvwDSdWgQR.py
areix_io/exchanges/xfxDTVyeMWfhKsoYHzybSSaSZwhxONMJ.py
areix_io/exchanges/ywcpmIORXbENpKwukOLSxOxYlaFolvwW.py
areix_io/utils/BgaTLZSFlKtvNUkLUEPVhGlRrrLGILTh.py
areix_io/utils/HsqzdwdtlESEuIlMRqWWKMvLLwGMdYqv.py
areix_io/utils/KrhOfolmxDldKCmNSFbWTAHCPIhwqfIi.py
areix_io/utils/SfrtTTUBturKxvWIHgFvPACUHOmeLiMg.py
areix_io/utils/__init__.py
areix_io/utils/auth.py
areix_io/utils/bKnwPutCXAifNGGgJRlAORRxmDujebLS.py
areix_io/utils/gMUsYMovSMjzpVmfMRlFvjqDCkYWFTHJ.py